{
  "result": {
    "soi_title": {
      "value": null,
      "citations": []
    },
    "as_of_date": {
      "value": "DECEMBER 31, 2004",
      "citations": [
        {
          "type": "Text",
          "bbox": {
            "left": 0.41759259259259257,
            "top": 0.0421875,
            "width": 0.15648148148148147,
            "height": 0.00625,
            "page": 1,
            "original_page": 1
          },
          "content": "DECEMBER 31, 2004",
          "image_url": null,
          "chart_data": null,
          "confidence": "high",
          "granular_confidence": {
            "extract_confidence": 1.0,
            "parse_confidence": 0.9176087081432343
          },
          "extra": null
        }
      ]
    },
    "reporting_basis": {
      "value": null,
      "citations": []
    },
    "soi_rows": {
      "value": null,
      "citations": []
    }
  },
  "usage": {
    "num_fields": 3,
    "num_pages": 8,
    "credits": 32.0
  },
  "job_id": "a6881979-e0b7-4344-9154-adebee0becda",
  "studio_link": "https://studio.reducto.ai/job/a6881979-e0b7-4344-9154-adebee0becda"
}